src/__init__.py
src/py.typed
src/cli/__init__.py
src/cli/cli.py
src/cli/logs.py
src/cli/main.py
src/core/__init__.py
src/core/constants.py
src/core/log_events.py
src/core/models.py
src/core/session_end_result.py
src/core/tool_name_extractor.py
src/core/protocols/__init__.py
src/core/protocols/infra.py
src/core/protocols/issue.py
src/core/protocols/lifecycle.py
src/core/protocols/log.py
src/core/protocols/review.py
src/core/protocols/sdk.py
src/core/protocols/validation.py
src/core/protocols/events/__init__.py
src/core/protocols/events/agent_lifecycle.py
src/core/protocols/events/dataclasses.py
src/core/protocols/events/diagnostics.py
src/core/protocols/events/gate_events.py
src/core/protocols/events/issue_lifecycle.py
src/core/protocols/events/run_lifecycle.py
src/core/protocols/events/sink.py
src/core/protocols/events/trigger_events.py
src/domain/__init__.py
src/domain/deadlock.py
src/domain/evidence_check.py
src/domain/lifecycle.py
src/domain/prompts.py
src/domain/validation/__init__.py
src/domain/validation/code_pattern_matcher.py
src/domain/validation/config.py
src/domain/validation/config_loader.py
src/domain/validation/config_merger.py
src/domain/validation/coverage.py
src/domain/validation/coverage_args.py
src/domain/validation/e2e.py
src/domain/validation/helpers.py
src/domain/validation/lint_cache.py
src/domain/validation/preset_registry.py
src/domain/validation/result.py
src/domain/validation/runner.py
src/domain/validation/spec.py
src/domain/validation/spec_executor.py
src/domain/validation/spec_result_builder.py
src/domain/validation/spec_runner.py
src/domain/validation/spec_workspace.py
src/domain/validation/validation_gating.py
src/domain/validation/worktree.py
src/domain/validation/presets/__init__.py
src/domain/validation/presets/gleam.yaml
src/domain/validation/presets/go.yaml
src/domain/validation/presets/node-npm.yaml
src/domain/validation/presets/python-uv.yaml
src/domain/validation/presets/rust.yaml
src/infra/__init__.py
mala_agent-1.1.6.dist-info/METADATA
mala_agent-1.1.6.dist-info/WHEEL
mala_agent-1.1.6.dist-info/entry_points.txt
mala_agent-1.1.6.dist-info/licenses/LICENSE.txt
mala_agent-1.1.6.dist-info/RECORD
