Metadata-Version: 2.4
Name: mala-agent
Version: 1.1.6
Summary: Agent SDK orchestrator for parallel issue processing
Project-URL: Repository, https://github.com/charlieyou/mala
Author: Charlie You
License-Expression: GPL-3.0-or-later
License-File: LICENSE.txt
Keywords: agent,ai,automation,orchestrator,sdk
Classifier: Development Status :: 3 - Alpha
Classifier: Intended Audience :: Developers
Classifier: License :: OSI Approved :: GNU General Public License v3 or later (GPLv3+)
Classifier: Programming Language :: Python :: 3
Classifier: Programming Language :: Python :: 3.11
Classifier: Programming Language :: Python :: 3.12
Requires-Python: >=3.11
Requires-Dist: claude-agent-sdk
Requires-Dist: python-dotenv>=1.0.0
Requires-Dist: pyyaml>=6.0
Requires-Dist: questionary>=2.0.0
Requires-Dist: tabulate>=0.9.0
Requires-Dist: typer>=0.9.0
Provides-Extra: dev
Requires-Dist: pytest-asyncio>=0.24.0; extra == 'dev'
Requires-Dist: pytest-cov>=5.0.0; extra == 'dev'
Requires-Dist: pytest>=8.0.0; extra == 'dev'
